wyrmx_core/__init__.py
wyrmx_core/app.py
wyrmx_core/db/__init__.py
wyrmx_core/db/base_model.py
wyrmx_core/db/base_schema.py
wyrmx_core/decorators.py
wyrmx_core/di/__init__.py
wyrmx_core/di/container.py
wyrmx_core/di/scope.py
wyrmx_core/http/__init__.py
wyrmx_core/http/request_methods.py
wyrmx_core/http/router.py
wyrmx_core/test.py
wyrmx_core-0.1.14.dist-info/METADATA
wyrmx_core-0.1.14.dist-info/WHEEL
wyrmx_core-0.1.14.dist-info/RECORD
