Metadata-Version: 2.3
Name: wyrmx-core
Version: 0.1.14
Summary: Wyrmx Core is the framework engine for Wyrmx, offering DI, decorators, routing, and architecture patterns on top of FastAPI.
Author: Yousri Aouledissa
Author-email: aouledissayousri@gmail.com
Requires-Python: >=3.13
Classifier: Programming Language :: Python :: 3
Classifier: Programming Language :: Python :: 3.13
Requires-Dist: fastapi (>=0.116.0)
Requires-Dist: httpx (>=0.28.1,<0.29.0)
Requires-Dist: sqlalchemy (>=2.0.41,<3.0.0)
